faust_avro/__init__.py
faust_avro/app.py
faust_avro/asyncio.py
faust_avro/context.py
faust_avro/exceptions.py
faust_avro/parsers/__init__.py
faust_avro/parsers/avro.py
faust_avro/parsers/faust.py
faust_avro/record.py
faust_avro/registry.py
faust_avro/schema.py
faust_avro/serializers.py
faust_avro/topic.py
faust_avro/types.py
faust_avro-0.4.1.dist-info/LICENSE
faust_avro-0.4.1.dist-info/WHEEL
faust_avro-0.4.1.dist-info/METADATA
faust_avro-0.4.1.dist-info/RECORD
