Metadata-Version: 2.1
Name: faust-avro
Version: 0.4.1
Summary: Avro codec and schema registry support for Faust
Home-page: https://github.com/masterysystems/faust-avro
License: BSD-3-Clause
Author: Mastery Systems LLC
Author-email: oss@mastery.net
Requires-Python: >=3.7,<4.0
Classifier: Development Status :: 3 - Alpha
Classifier: Intended Audience :: Developers
Classifier: License :: OSI Approved :: BSD License
Classifier: Programming Language :: Python :: 3
Classifier: Programming Language :: Python :: 3.7
Classifier: Programming Language :: Python :: 3.8
Classifier: Typing :: Typed
Requires-Dist: aiohttp (>=3.6,<4.0)
Requires-Dist: fastavro (>=0.22.5,<0.23.0)
Requires-Dist: faust (>=1.10,<2.0)
Requires-Dist: funcy (>=1.13,<2.0)
Requires-Dist: typing-inspect (>=0.5.0,<0.6.0)
Project-URL: Repository, https://github.com/masterysystems/faust-avro
